[{"title":"青蛙跳台阶","questions_id":"cy51s-cirofn-vxvrne-hgh3tk","json_path":"cy51s-cirofn-vxvrne-hgh3tk.json","subject_text":"node基础","subject_id":"4pu32-vs796l","exam_id":"jpg8y9-zbzt7o-jpvuhf-fwnjvr","exam_name":"周考2","user_name":"renyuliang","user_id":"bsz88g-071r5","questions_type_text":"手写代码","questions_type_id":"v8i73-r8oai","questions_stem":"用js实现青蛙跳台阶，一共十个台阶，青蛙每次跳一个或者两个台阶，打印出所有可能的跳跃方法（例如：[1,1,1,1,1,1,1,1,1,1]/[2,2,2,2,2]/[1,1,1,1,1,1,1,1,2]）","student_answer":"function fn(n) {\n    let arr = [];\n    for (var i = 0; i < n; i++) {\n        let num;\n        if (num = 1) {\n            for (var j = 0; j < n; j++) {\n                arr.push(num);\n            }\n        }\n    }\n    console.log(arr)\n}\nfn(10)"},{"title":"大小文件读取","questions_id":"z9ndnc-qhzc6-wb5vju-0pvnzk","json_path":"z9ndnc-qhzc6-wb5vju-0pvnzk.json","subject_text":"node基础","subject_id":"4pu32-vs796l","exam_id":"jpg8y9-zbzt7o-jpvuhf-fwnjvr","exam_name":"周考2","user_name":"w916peach","user_id":"axg8t2-oroeja","questions_type_text":"手写代码","questions_type_id":"v8i73-r8oai","questions_stem":"封装一个方法适配大小文件的读取，限定值2M","student_answer":"let copyFile = (tarpath, dirpath, size = 2000) => {\n    let status = fs.readFile(tarpath).size > size;\n    status ? copyBig(tarpath, dirpath) : copySmall(tarpath, dirpath)\n}\nlet copySmall = (tarpath, dirpath) => {\n    fs.readFile(tarpath, (err, data) => {\n        if (err) {\n            return err;\n        }\n        fs.writeFile(dirpath, data);\n    })\n}\nlet copyBig = (tarpath, dirpath) => {\n    let rs = fs.createReadStream(tarpath);\n    let ws = fs.createReadStream(dirpath);\n    rs.pipe(ws)\n}"},{"title":"实现多维数组转换为一维数组","questions_id":"60gn1-9nj3mi-hv4xz-t6ecp","json_path":"60gn1-9nj3mi-hv4xz-t6ecp.json","subject_text":"javaScript下","subject_id":"wl5yk-38c0g","exam_id":"ukmp9b-radddj-ogwdr-nw3ane","exam_name":"周考3","user_name":"renyuliang","user_id":"bsz88g-071r5","questions_type_text":"手写代码","questions_type_id":"v8i73-r8oai","questions_stem":"封装一个函数可以使得n维数组转换为1维数组，输出","student_answer":"var arr = [5,[2,[6,[4,9]]]]\nvar newAarr = []\nvar flat = function(arr) {\n    var length = arr.length\n    for (var index = 0; index < length; index++) {\n        var item = arr[index]\n        if (typeof item == \"object\") {\n            flat(item);\n        } else {\n            newAarr.push(item);\n        }\n    }\n}\nflat(arr);\nconsole.log(newAarr)"},{"title":"实现一个评星方法","questions_id":"tak6bp-2bpj3-xh6jpg-elkb8u","json_path":"tak6bp-2bpj3-xh6jpg-elkb8u.json","subject_text":"javaScript下","subject_id":"wl5yk-38c0g","exam_id":"ukmp9b-radddj-ogwdr-nw3ane","exam_name":"周考3","user_name":"liuyu","user_id":"kqpvys-hpzkdt","questions_type_text":"手写代码","questions_type_id":"v8i73-r8oai","questions_stem":"实现一个评星方法\n说明\n* 可根据传入的评分和总数，返回评星结果（用 ★ 和 ☆ 描述）\n* 评分必选项，四舍五入，总数可选，大于0的整数，默认为5\n* 对于评分为空或小于0、评分大于总数、总数小于0或总数非整数的情况，返回'errror'\n示例\n```\ngetRate(4); // ★★★★☆\ngetRate(4, 8); // ★★★★☆☆☆☆\ngetRate(3.4); //  ★★★☆☆\ngetRate(5, 2); // 'error'\ngetRate(-2); // 'error'\ngetRate(3, 5.5); // 'error'\n```\n\n\n\n\n\n\n\n\n\n\n\n","student_answer":"function fun(a, b) {\n    var num = b ? b : 5;\n    if (a > num || (!Math.isInteger(a))) {\n        return 'error';\n    }\n    let ct = Math.round(a);\n    for (var i = 0; i < num; i++) {\n        var x = document.createElement(\"span\");\n        x.innerHTML = \"★\";\n        box.appendChild(x);\n    }\n    var sp = document.querySelectorAll(\"#box span\");\n    for (var j = 0; j < ct; j++) {\n        sp[j].style.color = \"#aaa\"\n    }\n}"}]